{
  "paintings": [
    {
      "id": 1,
      "paint_title": "The Course of Empire: Destruction",
      "artist": "Thomas Cole",
      "year": 1836,
      "theme": "roman-history",
      "url": "https://upload.wikimedia.org/wikipedia/commons/6/64/Cole_Thomas_The_Course_of_Empire_Destruction_1836.jpg"
    },
    {
      "id": 2,
      "paint_title": "The Romans of the Decadence",
      "artist": "Thomas Couture",
      "year": 1847,
      "theme": "roman-history",
      "url": "https://upload.wikimedia.org/wikipedia/commons/b/b9/Thomas_Couture_-_Romans_during_the_Decadence_-_Google_Art_Project.jpg"
    },
    {
      "id": 3,
      "paint_title": "Pollice Verso",
      "artist": "Jean-Léon Gérôme",
      "year": 1872,
      "theme": "roman-history",
      "url": "https://upload.wikimedia.org/wikipedia/commons/c/c5/Jean-Leon_Gerome_Pollice_Verso.jpg"
    },
    {
      "id": 4,
      "paint_title": "The Triumph of Titus and Vespasian",
      "artist": "Sir Lawrence Alma-Tadema",
      "year": 1885,
      "theme": "roman-history",
      "url": "https://upload.wikimedia.org/wikipedia/commons/0/08/Romano_-_Triumph_of_Titus_and_Vespasian_02.jpg"
    },
    {
      "id": 5,
      "paint_title": "The Fire of Rome",
      "artist": "Hubert Robert",
      "year": 1785,
      "theme": "roman-history",
      "url": "https://upload.wikimedia.org/wikipedia/commons/3/3e/Robert%2C_Hubert_-_Incendie_%C3%A0_Rome_-.jpg"
    },
    {
      "id": 6,
      "paint_title": "Cleopatra before Caesar",
      "artist": "Jean-Léon Gérôme",
      "year": 1866,
      "theme": "roman-history",
      "url": "https://upload.wikimedia.org/wikipedia/commons/8/85/Cleopatra_and_Caesar_%28Jean-L%C3%A9on_G%C3%A9r%C3%B4me%29.jpg"
    },
    {
      "id": 7,
      "paint_title": "The Death of Caesar",
      "artist": "Vincenzo Camuccini",
      "year": 1798,
      "theme": "roman-history",
      "url": "https://upload.wikimedia.org/wikipedia/commons/3/3e/La_mort_de_C%C3%A9sar_-_Vincenzo_Camuccini.jpg"
    },
    {
      "id": 8,
      "paint_title": "The Baths of Caracalla",
      "artist": "Lawrence Alma-Tadema",
      "year": 1899,
      "theme": "roman-history",
      "url": "https://upload.wikimedia.org/wikipedia/commons/2/22/Sir_Lawrence_Alma-Tadema_-_The_Tepidarium.jpg"
    },
    {
      "id": 9,
      "paint_title": "The Last Day of Pompeii",
      "artist": "Karl Bryullov",
      "year": 1833,
      "theme": "roman-history",
      "url": "https://upload.wikimedia.org/wikipedia/commons/3/38/Karl_Brullov_-_The_Last_Day_of_Pompeii_-_Google_Art_Project.jpg"
    },
    {
      "id": 10,
      "paint_title": "The Triumph of Caesar",
      "artist": "Andrea Mantegna",
      "year": "1484-1492",
      "theme": "roman-history",
      "url": "https://upload.wikimedia.org/wikipedia/commons/9/9a/Mantegna%2C_trionfo_di_cesare%2C_04.jpg"
    },
    {
      "id": 11,
      "paint_title": "The Triumph of Titus: The Flavians",
      "artist": "Sir Lawrence Alma-Tadema",
      "year": 1885,
      "theme": "roman-history",
      "url": "https://upload.wikimedia.org/wikipedia/commons/0/0a/Sir_Lawrence_Alma-Tadema%2C_RA%2C_OM_-_The_Triumph_of_Titus_-_The_Flavians_-_Walters_3731.jpg"
    }, 
    

  ]
}
